agentbox/__init__.py
vital_agentbox-0.0.1.dist-info/LICENSE
vital_agentbox-0.0.1.dist-info/METADATA
vital_agentbox-0.0.1.dist-info/WHEEL
vital_agentbox-0.0.1.dist-info/top_level.txt
vital_agentbox-0.0.1.dist-info/RECORD
