Metadata-Version: 2.2
Name: vital-agentbox
Version: 0.0.1
Summary: Vital Agent Box
Home-page: https://github.com/vital-ai/vital-agentbox
Author: Marc Hadfield
Author-email: marc@vital.ai
License: Apache License 2.0
Classifier: Programming Language :: Python :: 3.11
Classifier: License :: OSI Approved :: Apache Software License
Classifier: Operating System :: OS Independent
Requires-Python: >=3.11
License-File: LICENSE
Requires-Dist: vital-ai-vitalsigns>=0.1.27
Requires-Dist: vital-ai-domain>=0.1.4
Dynamic: author
Dynamic: author-email
Dynamic: classifier
Dynamic: description
Dynamic: description-content-type
Dynamic: home-page
Dynamic: license
Dynamic: requires-dist
Dynamic: requires-python
Dynamic: summary
